ethconnect/Account.py
ethconnect/EllipticCurve.py
ethconnect/EthAccount.py
ethconnect/EthConnect.py
ethconnect/EthTransaction.py
ethconnect/Keyring.py
ethconnect/ZymbitEthKeyring.py
ethconnect/ZymbitKeyringManager.py
ethconnect/__init__.py
ethconnect-1.1.1.dist-info/METADATA
ethconnect-1.1.1.dist-info/WHEEL
ethconnect-1.1.1.dist-info/licenses/LICENSE.md
ethconnect-1.1.1.dist-info/RECORD
