Metadata-Version: 2.1
Name: ethconnect
Version: 1.1.1
Summary: ETH-Connect Python SDK
Project-URL: Homepage, https://github.com/Zymbit-Wallet/ETH-Connect-PY
Author-email: Shivaansh Kapoor <shiv@zymbit.com>
License-File: LICENSE.md
Classifier: License :: OSI Approved :: Apache Software License
Classifier: Operating System :: OS Independent
Classifier: Programming Language :: Python :: 3
Requires-Python: >=3.7
